{
    "WWNR": ["(WWN&&~EWNR)"],
    "WWYR": [
        "~EUUYNR", "Z3WR", "~6-WLR", "6-WWR"
    ],
    "Z3WR": [
        "~EUUYNR", "~WWYR",
        {
            "op": "||",
            "val": [
                "(4-Z1WR&&4-WLR)",
                "(5-Z1WR&&5-WLR)",
                "(6-Z1WR&&6-WLR)"
            ]
        },
        "((~4-WWR&&~5-WWR)||Z3WR)"
    ],
    "4-W_N_LR": {
        "op": "||",
        "val": [
            "(~4-W_R_LR&&4-W_N_LR)",
            {
                "op": "&&",
                "val": ["4-W_R_LR",
                    "~OV11-Z2U_R_R", "~OV10/1-Z2U_R_R", "~OV10/2-Z2U_R_R",
                    "4-AU_N_S", "4-BU_N_S",
                    "(~4-_R_WLR1||~4-_N_WLR1)",
                    "~4-U_R_LR",
                    "~4-Z2WR1", "~4-Z2WR2"
                ]
            }
        ]
    },
    "5-W_N_LR": {
        "op": "||",
        "val": [
            "(~5-W_R_LR&&5-W_N_LR)",
            {
                "op": "&&",
                "val": ["5-W_R_LR",
                    "~OV2-Z2U_R_R", "~OV3/1-Z2U_R_R", "~OV3/2-Z2U_R_R",
                    "~5-AU_R_S", "5-BU_N_S", "6-AU_N_S",
                    "(~5-_R_WLR1||~5-_N_WLR1)",
                    "~5-U_R_LR",
                    "~5-Z2WR1", "~5-Z2WR2"
                ]
            }
        ]
    },
    "6-W_N_LR": {
        "op": "||",
        "val": [
            "(~6-W_R_LR&&6-W_N_LR)",
            {
                "op": "&&",
                "val": ["6-W_R_LR",
                    "~OV3/1-Z2U_R_R", "~OV3/2-Z2U_R_R",
                    "5-BU_N_S", "6-AU_N_S",
                    "(~6-_R_WLR1||~6-_N_WLR1)",
                    "~6-U_R_LR",
                    "~6-Z2WR1", "~6-Z2WR2"
                ]
            }
        ]
    },
    "4-WWR": [
        "~EUUYNR", "Z3WR",
        "~6-WWR", "~WWYR"
    ],
    "5-WWR": [
        "~EUUYNR", "Z3WR",
        "(4-WWR||5-WWR)",
        "~WWYR"
    ],
    "6-WWR": [
        "~EUUYNR", "Z3WR",
        "((~4-WLR&&~4-WLR&&5-WWR)||6-WWR)",
        "~WWYR"
    ]
}
