[
    [
        {
            "tag": "div",
            "text": [
                {
                    "tag": "button",
                    "value": "S1-GNR=1,MT-UNR=1",
                    "className": "evt signal_route_btn",
                    "text": "S1-MT"
                },
                {
                    "tag": "button",
                    "value": "S1-GNR=1,LT-UNR=1",
                    "className": "evt signal_route_btn",
                    "text": "S1-LT"
                },
                {
                    "tag": "button",
                    "value": "S1-GNR=1,LAT-UNR=1",
                    "className": "evt signal_route_btn",
                    "text": "S1-LAT"
                },
                {
                    "tag": "button",
                    "value": "S2-GNR=1,9-UNR=1",
                    "className": "evt signal_route_btn",
                    "text": "S2-9"
                },
                {
                    "tag": "button",
                    "value": "S3-GNR=1,9-UNR=1",
                    "className": "evt signal_route_btn",
                    "text": "S3-9"
                },
                {
                    "tag": "button",
                    "value": "S4-GNR=1,4-UNR=1",
                    "className": "evt signal_route_btn",
                    "text": "S4-4"
                }
            ]
        },
        {
            "tag": "div",
            "text": ""
        },
        {
            "tag": "div",
            "text": ""
        }
    ],
    [
        {
            "tag": "div",
            "text": [
                {
                    "tag": "button",
                    "value": "S13-GNR=1,MT-UNR=1",
                    "className": "evt signal_route_btn",
                    "text": "S13-MT"
                },
                {
                    "tag": "button",
                    "value": "S13-GNR=1,LT-UNR=1",
                    "className": "evt signal_route_btn",
                    "text": "S13-LT"
                },
                {
                    "tag": "button",
                    "value": "S13-GNR=1,LAT-UNR=1",
                    "className": "evt signal_route_btn",
                    "text": "S13-LAT"
                },
                {
                    "tag": "button",
                    "value": "S14-GNR=1,8-UNR=1",
                    "className": "evt signal_route_btn",
                    "text": "S14-8"
                },
                {
                    "tag": "button",
                    "value": "S15-GNR=1,8-UNR=1",
                    "className": "evt signal_route_btn",
                    "text": "S15-8"
                },
                {
                    "tag": "button",
                    "value": "S16-GNR=1,16-UNR=1",
                    "className": "evt signal_route_btn",
                    "text": "S16-16"
                }
            ]
        },
        {
            "tag": "div",
            "text": ""
        },
        {
            "tag": "div",
            "text": {
                "tag": "span",
                "className": "alert-danger badge",
                "text": ""
            }
        }
    ]
]